{
 "creation": "2025-09-07 07:08:46.031035",
 "disabled": 0,
 "docstatus": 0,
 "doctype": "Financial Report Template",
 "idx": 0,
 "modified": "2025-10-14 03:35:49.918519",
 "modified_by": "Administrator",
 "module": "Accounts",
 "name": "Horizontal Profit and Loss (Columnar)",
 "owner": "Administrator",
 "report_type": "Profit and Loss Statement",
 "rows": [
  {
   "advanced_filtering": 0,
   "balance_type": "",
   "bold_text": 1,
   "data_source": "Section Break",
   "display_name": "TRADING ACCOUNT",
   "fieldtype": "",
   "hidden_calculation": 0,
   "hide_when_empty": 0,
   "include_in_charts": 0,
   "indentation_level": 0,
   "italic_text": 0,
   "reverse_sign": 0
  },
  {
   "advanced_filtering": 0,
   "balance_type": "",
   "bold_text": 0,
   "data_source": "Column Break",
   "display_name": "Expenses",
   "fieldtype": "",
   "hidden_calculation": 0,
   "hide_when_empty": 0,
   "include_in_charts": 0,
   "indentation_level": 0,
   "italic_text": 0,
   "reverse_sign": 0
  },
  {
   "advanced_filtering": 0,
   "balance_type": "",
   "bold_text": 0,
   "data_source": "Blank Line",
   "fieldtype": "",
   "hidden_calculation": 0,
   "hide_when_empty": 0,
   "include_in_charts": 0,
   "indentation_level": 0,
   "italic_text": 0,
   "reverse_sign": 0
  },
  {
   "advanced_filtering": 0,
   "balance_type": "Opening Balance",
   "bold_text": 0,
   "calculation_formula": "[\"account_category\", \"=\", \"Stock Assets\"]",
   "data_source": "Account Data",
   "display_name": "Opening Stock",
   "fieldtype": "",
   "hidden_calculation": 0,
   "hide_when_empty": 0,
   "include_in_charts": 0,
   "indentation_level": 0,
   "italic_text": 0,
   "reference_code": "EXP_OPENING_STOCK",
   "reverse_sign": 0
  },
  {
   "advanced_filtering": 0,
   "balance_type": "Period Movement (Debits - Credits)",
   "bold_text": 0,
   "calculation_formula": "[\"account_category\", \"=\", \"Cost of Goods Sold\"]",
   "data_source": "Account Data",
   "display_name": "Cost of Goods Sold",
   "fieldtype": "",
   "hidden_calculation": 1,
   "hide_when_empty": 0,
   "include_in_charts": 0,
   "indentation_level": 0,
   "italic_text": 0,
   "reference_code": "EXP_COGS",
   "reverse_sign": 0
  },
  {
   "advanced_filtering": 0,
   "balance_type": "",
   "bold_text": 0,
   "calculation_formula": "INC_CLOSING_STOCK + EXP_COGS - EXP_OPENING_STOCK",
   "data_source": "Calculated Amount",
   "display_name": "Purchases",
   "fieldtype": "",
   "hidden_calculation": 0,
   "hide_when_empty": 0,
   "include_in_charts": 0,
   "indentation_level": 0,
   "italic_text": 0,
   "reference_code": "EXP_PURCHASES",
   "reverse_sign": 0
  },
  {
   "advanced_filtering": 0,
   "balance_type": "Period Movement (Debits - Credits)",
   "bold_text": 0,
   "calculation_formula": "[\"account_category\", \"=\", \"Other Direct Costs\"]",
   "data_source": "Account Data",
   "display_name": "Direct Expenses",
   "fieldtype": "",
   "hidden_calculation": 0,
   "hide_when_empty": 1,
   "include_in_charts": 0,
   "indentation_level": 0,
   "italic_text": 0,
   "reference_code": "EXP_DIRECT",
   "reverse_sign": 0
  },
  {
   "advanced_filtering": 0,
   "balance_type": "",
   "bold_text": 0,
   "calculation_formula": "EXP_OPENING_STOCK + EXP_PURCHASES + EXP_DIRECT",
   "data_source": "Calculated Amount",
   "display_name": "Subtotal",
   "fieldtype": "",
   "hidden_calculation": 0,
   "hide_when_empty": 0,
   "include_in_charts": 0,
   "indentation_level": 0,
   "italic_text": 1,
   "reference_code": "LEFT_SUBTOTAL_1",
   "reverse_sign": 0
  },
  {
   "advanced_filtering": 0,
   "balance_type": "",
   "bold_text": 0,
   "data_source": "Blank Line",
   "fieldtype": "",
   "hidden_calculation": 0,
   "hide_when_empty": 0,
   "include_in_charts": 0,
   "indentation_level": 0,
   "italic_text": 0,
   "reverse_sign": 0
  },
  {
   "advanced_filtering": 0,
   "balance_type": "",
   "bold_text": 1,
   "calculation_formula": "max(0, RIGHT_SUBTOTAL_1 - LEFT_SUBTOTAL_1)",
   "color": "#28a745",
   "data_source": "Calculated Amount",
   "display_name": "Gross Profit c/d",
   "fieldtype": "",
   "hidden_calculation": 0,
   "hide_when_empty": 1,
   "include_in_charts": 0,
   "indentation_level": 0,
   "italic_text": 0,
   "reference_code": "GP_CD_LEFT",
   "reverse_sign": 0
  },
  {
   "advanced_filtering": 0,
   "balance_type": "",
   "bold_text": 0,
   "data_source": "Column Break",
   "display_name": "Income",
   "fieldtype": "",
   "hidden_calculation": 0,
   "hide_when_empty": 0,
   "include_in_charts": 0,
   "indentation_level": 0,
   "italic_text": 0,
   "reverse_sign": 0
  },
  {
   "advanced_filtering": 0,
   "balance_type": "",
   "bold_text": 0,
   "data_source": "Blank Line",
   "fieldtype": "",
   "hidden_calculation": 0,
   "hide_when_empty": 0,
   "include_in_charts": 0,
   "indentation_level": 0,
   "italic_text": 0,
   "reverse_sign": 0
  },
  {
   "advanced_filtering": 0,
   "balance_type": "Period Movement (Debits - Credits)",
   "bold_text": 0,
   "calculation_formula": "{\"and\":[[\"account_category\",\"=\",\"Revenue from Operations\"],[\"account_name\",\"not like\",\"%Service%\"]]}",
   "data_source": "Account Data",
   "display_name": "Sales",
   "fieldtype": "",
   "hidden_calculation": 0,
   "hide_when_empty": 0,
   "include_in_charts": 0,
   "indentation_level": 0,
   "italic_text": 0,
   "reference_code": "INC_SALES",
   "reverse_sign": 1
  },
  {
   "advanced_filtering": 0,
   "balance_type": "Closing Balance",
   "bold_text": 0,
   "calculation_formula": "[\"account_category\", \"=\", \"Stock Assets\"]",
   "data_source": "Account Data",
   "display_name": "Closing Stock",
   "fieldtype": "",
   "hidden_calculation": 0,
   "hide_when_empty": 0,
   "include_in_charts": 0,
   "indentation_level": 0,
   "italic_text": 0,
   "reference_code": "INC_CLOSING_STOCK",
   "reverse_sign": 0
  },
  {
   "advanced_filtering": 0,
   "balance_type": "Period Movement (Debits - Credits)",
   "bold_text": 0,
   "calculation_formula": "{\"and\": [[\"account_category\", \"=\", \"Revenue from Operations\"], [\"account_name\", \"like\", \"Service\"]]}",
   "data_source": "Account Data",
   "display_name": "Service Income",
   "fieldtype": "",
   "hidden_calculation": 0,
   "hide_when_empty": 1,
   "include_in_charts": 0,
   "indentation_level": 0,
   "italic_text": 0,
   "reference_code": "INC_SERVICE",
   "reverse_sign": 1
  },
  {
   "advanced_filtering": 0,
   "balance_type": "",
   "bold_text": 0,
   "calculation_formula": "INC_SALES + INC_CLOSING_STOCK + INC_SERVICE",
   "data_source": "Calculated Amount",
   "display_name": "Subtotal",
   "fieldtype": "",
   "hidden_calculation": 0,
   "hide_when_empty": 0,
   "include_in_charts": 0,
   "indentation_level": 0,
   "italic_text": 1,
   "reference_code": "RIGHT_SUBTOTAL_1",
   "reverse_sign": 0
  },
  {
   "advanced_filtering": 0,
   "balance_type": "",
   "bold_text": 0,
   "data_source": "Blank Line",
   "fieldtype": "",
   "hidden_calculation": 0,
   "hide_when_empty": 0,
   "include_in_charts": 0,
   "indentation_level": 0,
   "italic_text": 0,
   "reverse_sign": 0
  },
  {
   "advanced_filtering": 0,
   "balance_type": "",
   "bold_text": 1,
   "calculation_formula": "max(0, LEFT_SUBTOTAL_1 - RIGHT_SUBTOTAL_1)",
   "color": "#CB2929",
   "data_source": "Calculated Amount",
   "display_name": "Gross Loss c/d",
   "fieldtype": "",
   "hidden_calculation": 0,
   "hide_when_empty": 1,
   "include_in_charts": 0,
   "indentation_level": 0,
   "italic_text": 0,
   "reference_code": "GL_CD_RIGHT",
   "reverse_sign": 0
  },
  {
   "advanced_filtering": 0,
   "balance_type": "",
   "bold_text": 0,
   "data_source": "Section Break",
   "fieldtype": "",
   "hidden_calculation": 0,
   "hide_when_empty": 0,
   "include_in_charts": 0,
   "indentation_level": 0,
   "italic_text": 0,
   "reverse_sign": 0
  },
  {
   "advanced_filtering": 0,
   "balance_type": "",
   "bold_text": 0,
   "data_source": "Blank Line",
   "fieldtype": "",
   "hidden_calculation": 0,
   "hide_when_empty": 0,
   "include_in_charts": 0,
   "indentation_level": 0,
   "italic_text": 0,
   "reverse_sign": 0
  },
  {
   "advanced_filtering": 0,
   "balance_type": "",
   "bold_text": 1,
   "calculation_formula": "LEFT_SUBTOTAL_1 + GP_CD_LEFT",
   "data_source": "Calculated Amount",
   "display_name": "Total",
   "fieldtype": "",
   "hidden_calculation": 0,
   "hide_when_empty": 0,
   "include_in_charts": 0,
   "indentation_level": 0,
   "italic_text": 0,
   "reference_code": "LEFT_TOTAL_1",
   "reverse_sign": 0
  },
  {
   "advanced_filtering": 0,
   "balance_type": "",
   "bold_text": 0,
   "data_source": "Blank Line",
   "fieldtype": "",
   "hidden_calculation": 0,
   "hide_when_empty": 0,
   "include_in_charts": 0,
   "indentation_level": 0,
   "italic_text": 0,
   "reverse_sign": 0
  },
  {
   "advanced_filtering": 0,
   "balance_type": "",
   "bold_text": 0,
   "data_source": "Column Break",
   "fieldtype": "",
   "hidden_calculation": 0,
   "hide_when_empty": 0,
   "include_in_charts": 0,
   "indentation_level": 0,
   "italic_text": 0,
   "reverse_sign": 0
  },
  {
   "advanced_filtering": 0,
   "balance_type": "",
   "bold_text": 0,
   "data_source": "Blank Line",
   "fieldtype": "",
   "hidden_calculation": 0,
   "hide_when_empty": 0,
   "include_in_charts": 0,
   "indentation_level": 0,
   "italic_text": 0,
   "reverse_sign": 0
  },
  {
   "advanced_filtering": 0,
   "balance_type": "",
   "bold_text": 1,
   "calculation_formula": "RIGHT_SUBTOTAL_1 + GL_CD_RIGHT",
   "data_source": "Calculated Amount",
   "display_name": "Total",
   "fieldtype": "",
   "hidden_calculation": 0,
   "hide_when_empty": 0,
   "include_in_charts": 0,
   "indentation_level": 0,
   "italic_text": 0,
   "reference_code": "RIGHT_TOTAL_1",
   "reverse_sign": 0
  },
  {
   "advanced_filtering": 0,
   "balance_type": "",
   "bold_text": 0,
   "data_source": "Blank Line",
   "fieldtype": "",
   "hidden_calculation": 0,
   "hide_when_empty": 0,
   "include_in_charts": 0,
   "indentation_level": 0,
   "italic_text": 0,
   "reverse_sign": 0
  },
  {
   "advanced_filtering": 0,
   "balance_type": "",
   "bold_text": 0,
   "calculation_formula": "LEFT_TOTAL_1 - RIGHT_TOTAL_1",
   "color": "#EC864B",
   "data_source": "Calculated Amount",
   "display_name": "Trading Balance Check (should be zero)",
   "fieldtype": "",
   "hidden_calculation": 0,
   "hide_when_empty": 1,
   "include_in_charts": 0,
   "indentation_level": 0,
   "italic_text": 1,
   "reference_code": "TRADING_VALIDATION",
   "reverse_sign": 0
  },
  {
   "advanced_filtering": 0,
   "balance_type": "",
   "bold_text": 1,
   "data_source": "Section Break",
   "display_name": "PROFIT & LOSS ACCOUNT",
   "fieldtype": "",
   "hidden_calculation": 0,
   "hide_when_empty": 0,
   "include_in_charts": 0,
   "indentation_level": 0,
   "italic_text": 0,
   "reverse_sign": 0
  },
  {
   "advanced_filtering": 0,
   "balance_type": "",
   "bold_text": 0,
   "data_source": "Column Break",
   "display_name": "P&L Expenses",
   "fieldtype": "",
   "hidden_calculation": 0,
   "hide_when_empty": 0,
   "include_in_charts": 0,
   "indentation_level": 0,
   "italic_text": 0,
   "reverse_sign": 0
  },
  {
   "advanced_filtering": 0,
   "balance_type": "",
   "bold_text": 0,
   "data_source": "Blank Line",
   "fieldtype": "",
   "hidden_calculation": 0,
   "hide_when_empty": 0,
   "include_in_charts": 0,
   "indentation_level": 0,
   "italic_text": 0,
   "reverse_sign": 0
  },
  {
   "advanced_filtering": 0,
   "balance_type": "",
   "bold_text": 1,
   "calculation_formula": "GL_CD_RIGHT",
   "color": "#CB2929",
   "data_source": "Calculated Amount",
   "display_name": "Gross Loss b/d",
   "fieldtype": "",
   "hidden_calculation": 0,
   "hide_when_empty": 1,
   "include_in_charts": 0,
   "indentation_level": 0,
   "italic_text": 0,
   "reference_code": "GL_BD_LEFT",
   "reverse_sign": 0
  },
  {
   "advanced_filtering": 0,
   "balance_type": "Period Movement (Debits - Credits)",
   "bold_text": 0,
   "calculation_formula": "{\"and\": [[\"account_category\", \"=\", \"Operating Expenses\"], [\"account_name\", \"like\", \"Administrative\"]]}",
   "data_source": "Account Data",
   "display_name": "Administrative Expenses",
   "fieldtype": "",
   "hidden_calculation": 0,
   "hide_when_empty": 0,
   "include_in_charts": 0,
   "indentation_level": 0,
   "italic_text": 0,
   "reference_code": "EXP_ADMIN",
   "reverse_sign": 0
  },
  {
   "advanced_filtering": 0,
   "balance_type": "Period Movement (Debits - Credits)",
   "bold_text": 0,
   "calculation_formula": "{\"and\": [[\"account_category\", \"=\", \"Operating Expenses\"], [\"account_name\", \"like\", \"Sales\"]]}",
   "data_source": "Account Data",
   "display_name": "Selling & Distribution Expenses",
   "fieldtype": "",
   "hidden_calculation": 0,
   "hide_when_empty": 0,
   "include_in_charts": 0,
   "indentation_level": 0,
   "italic_text": 0,
   "reference_code": "EXP_SELLING",
   "reverse_sign": 0
  },
  {
   "advanced_filtering": 0,
   "balance_type": "Period Movement (Debits - Credits)",
   "bold_text": 0,
   "calculation_formula": "[\"account_category\", \"=\", \"Finance Costs\"]",
   "data_source": "Account Data",
   "display_name": "Finance Costs",
   "fieldtype": "",
   "hidden_calculation": 0,
   "hide_when_empty": 0,
   "include_in_charts": 0,
   "indentation_level": 0,
   "italic_text": 0,
   "reference_code": "EXP_FINANCE",
   "reverse_sign": 0
  },
  {
   "advanced_filtering": 0,
   "balance_type": "Period Movement (Debits - Credits)",
   "bold_text": 0,
   "calculation_formula": "[\"account_type\", \"like\", \"Depreciation\"]",
   "data_source": "Account Data",
   "display_name": "Depreciation",
   "fieldtype": "",
   "hidden_calculation": 0,
   "hide_when_empty": 0,
   "include_in_charts": 0,
   "indentation_level": 0,
   "italic_text": 0,
   "reference_code": "EXP_DEPRECIATION",
   "reverse_sign": 0
  },
  {
   "advanced_filtering": 0,
   "balance_type": "Period Movement (Debits - Credits)",
   "bold_text": 0,
   "calculation_formula": "{\"and\": [[\"account_category\", \"=\", \"Operating Expenses\"], [\"account_name\", \"not like\", \"Administrative\"], [\"account_name\", \"not like\", \"Sales\"], [\"account_type\", \"not like\", \"Depreciation\"]]}",
   "data_source": "Account Data",
   "display_name": "Other Expenses",
   "fieldtype": "",
   "hidden_calculation": 0,
   "hide_when_empty": 1,
   "include_in_charts": 0,
   "indentation_level": 0,
   "italic_text": 0,
   "reference_code": "EXP_OTHER",
   "reverse_sign": 0
  },
  {
   "advanced_filtering": 0,
   "balance_type": "Period Movement (Debits - Credits)",
   "bold_text": 0,
   "calculation_formula": "[\"account_category\", \"=\", \"Tax Expense\"]",
   "data_source": "Account Data",
   "display_name": "Provision for Tax",
   "fieldtype": "",
   "hidden_calculation": 0,
   "hide_when_empty": 0,
   "include_in_charts": 0,
   "indentation_level": 0,
   "italic_text": 0,
   "reference_code": "EXP_TAX",
   "reverse_sign": 0
  },
  {
   "advanced_filtering": 0,
   "balance_type": "",
   "bold_text": 0,
   "calculation_formula": "GL_BD_LEFT + EXP_ADMIN + EXP_SELLING + EXP_FINANCE + EXP_DEPRECIATION + EXP_OTHER + EXP_TAX",
   "data_source": "Calculated Amount",
   "display_name": "Subtotal",
   "fieldtype": "",
   "hidden_calculation": 0,
   "hide_when_empty": 0,
   "include_in_charts": 0,
   "indentation_level": 0,
   "italic_text": 1,
   "reference_code": "LEFT_SUBTOTAL_2",
   "reverse_sign": 0
  },
  {
   "advanced_filtering": 0,
   "balance_type": "",
   "bold_text": 0,
   "data_source": "Blank Line",
   "fieldtype": "",
   "hidden_calculation": 0,
   "hide_when_empty": 0,
   "include_in_charts": 0,
   "indentation_level": 0,
   "italic_text": 0,
   "reverse_sign": 0
  },
  {
   "advanced_filtering": 0,
   "balance_type": "",
   "bold_text": 1,
   "calculation_formula": "max(0, RIGHT_SUBTOTAL_2 - LEFT_SUBTOTAL_2)",
   "color": "#28a745",
   "data_source": "Calculated Amount",
   "display_name": "Net Profit",
   "fieldtype": "",
   "hidden_calculation": 0,
   "hide_when_empty": 1,
   "include_in_charts": 0,
   "indentation_level": 0,
   "italic_text": 0,
   "reference_code": "NET_PROFIT_LEFT",
   "reverse_sign": 0
  },
  {
   "advanced_filtering": 0,
   "balance_type": "",
   "bold_text": 0,
   "data_source": "Column Break",
   "display_name": "P&L Income",
   "fieldtype": "",
   "hidden_calculation": 0,
   "hide_when_empty": 0,
   "include_in_charts": 0,
   "indentation_level": 0,
   "italic_text": 0,
   "reverse_sign": 0
  },
  {
   "advanced_filtering": 0,
   "balance_type": "",
   "bold_text": 0,
   "data_source": "Blank Line",
   "fieldtype": "",
   "hidden_calculation": 0,
   "hide_when_empty": 0,
   "include_in_charts": 0,
   "indentation_level": 0,
   "italic_text": 0,
   "reverse_sign": 0
  },
  {
   "advanced_filtering": 0,
   "balance_type": "",
   "bold_text": 1,
   "calculation_formula": "GP_CD_LEFT",
   "color": "#28a745",
   "data_source": "Calculated Amount",
   "display_name": "Gross Profit b/d",
   "fieldtype": "",
   "hidden_calculation": 0,
   "hide_when_empty": 1,
   "include_in_charts": 0,
   "indentation_level": 0,
   "italic_text": 0,
   "reference_code": "GP_BD_RIGHT",
   "reverse_sign": 0
  },
  {
   "advanced_filtering": 0,
   "balance_type": "Period Movement (Debits - Credits)",
   "bold_text": 0,
   "calculation_formula": "[\"account_category\", \"=\", \"Other Operating Income\"]",
   "data_source": "Account Data",
   "display_name": "Other Income",
   "fieldtype": "",
   "hidden_calculation": 0,
   "hide_when_empty": 0,
   "include_in_charts": 0,
   "indentation_level": 0,
   "italic_text": 0,
   "reference_code": "INC_OTHER",
   "reverse_sign": 1
  },
  {
   "advanced_filtering": 0,
   "balance_type": "Period Movement (Debits - Credits)",
   "bold_text": 0,
   "calculation_formula": "[\"account_category\", \"=\", \"Investment Income\"]",
   "data_source": "Account Data",
   "display_name": "Investment Income",
   "fieldtype": "",
   "hidden_calculation": 0,
   "hide_when_empty": 0,
   "include_in_charts": 0,
   "indentation_level": 0,
   "italic_text": 0,
   "reference_code": "INC_INVESTMENT",
   "reverse_sign": 1
  },
  {
   "advanced_filtering": 0,
   "balance_type": "",
   "bold_text": 0,
   "calculation_formula": "GP_BD_RIGHT + INC_OTHER + INC_INVESTMENT",
   "data_source": "Calculated Amount",
   "display_name": "Subtotal",
   "fieldtype": "",
   "hidden_calculation": 0,
   "hide_when_empty": 0,
   "include_in_charts": 0,
   "indentation_level": 0,
   "italic_text": 1,
   "reference_code": "RIGHT_SUBTOTAL_2",
   "reverse_sign": 0
  },
  {
   "advanced_filtering": 0,
   "balance_type": "",
   "bold_text": 0,
   "data_source": "Blank Line",
   "fieldtype": "",
   "hidden_calculation": 0,
   "hide_when_empty": 0,
   "include_in_charts": 0,
   "indentation_level": 0,
   "italic_text": 0,
   "reverse_sign": 0
  },
  {
   "advanced_filtering": 0,
   "balance_type": "",
   "bold_text": 1,
   "calculation_formula": "max(0, LEFT_SUBTOTAL_2 - RIGHT_SUBTOTAL_2)",
   "color": "#CB2929",
   "data_source": "Calculated Amount",
   "display_name": "Net Loss",
   "fieldtype": "",
   "hidden_calculation": 0,
   "hide_when_empty": 1,
   "include_in_charts": 0,
   "indentation_level": 0,
   "italic_text": 0,
   "reference_code": "NET_LOSS_RIGHT",
   "reverse_sign": 0
  },
  {
   "advanced_filtering": 0,
   "balance_type": "",
   "bold_text": 0,
   "data_source": "Section Break",
   "fieldtype": "",
   "hidden_calculation": 0,
   "hide_when_empty": 0,
   "include_in_charts": 0,
   "indentation_level": 0,
   "italic_text": 0,
   "reverse_sign": 0
  },
  {
   "advanced_filtering": 0,
   "balance_type": "",
   "bold_text": 0,
   "data_source": "Blank Line",
   "fieldtype": "",
   "hidden_calculation": 0,
   "hide_when_empty": 0,
   "include_in_charts": 0,
   "indentation_level": 0,
   "italic_text": 0,
   "reverse_sign": 0
  },
  {
   "advanced_filtering": 0,
   "balance_type": "",
   "bold_text": 1,
   "calculation_formula": "LEFT_SUBTOTAL_2 + NET_PROFIT_LEFT",
   "data_source": "Calculated Amount",
   "display_name": "Total",
   "fieldtype": "",
   "hidden_calculation": 0,
   "hide_when_empty": 0,
   "include_in_charts": 0,
   "indentation_level": 0,
   "italic_text": 0,
   "reference_code": "LEFT_TOTAL_2",
   "reverse_sign": 0
  },
  {
   "advanced_filtering": 0,
   "balance_type": "",
   "bold_text": 0,
   "data_source": "Column Break",
   "fieldtype": "",
   "hidden_calculation": 0,
   "hide_when_empty": 0,
   "include_in_charts": 0,
   "indentation_level": 0,
   "italic_text": 0,
   "reverse_sign": 0
  },
  {
   "advanced_filtering": 0,
   "balance_type": "",
   "bold_text": 0,
   "data_source": "Blank Line",
   "fieldtype": "",
   "hidden_calculation": 0,
   "hide_when_empty": 0,
   "include_in_charts": 0,
   "indentation_level": 0,
   "italic_text": 0,
   "reverse_sign": 0
  },
  {
   "advanced_filtering": 0,
   "balance_type": "",
   "bold_text": 1,
   "calculation_formula": "RIGHT_SUBTOTAL_2 + NET_LOSS_RIGHT",
   "data_source": "Calculated Amount",
   "display_name": "Total",
   "fieldtype": "",
   "hidden_calculation": 0,
   "hide_when_empty": 0,
   "include_in_charts": 0,
   "indentation_level": 0,
   "italic_text": 0,
   "reference_code": "RIGHT_TOTAL_2",
   "reverse_sign": 0
  },
  {
   "advanced_filtering": 0,
   "balance_type": "",
   "bold_text": 0,
   "data_source": "Section Break",
   "fieldtype": "",
   "hidden_calculation": 0,
   "hide_when_empty": 0,
   "include_in_charts": 0,
   "indentation_level": 0,
   "italic_text": 0,
   "reverse_sign": 0
  },
  {
   "advanced_filtering": 0,
   "balance_type": "",
   "bold_text": 0,
   "calculation_formula": "LEFT_TOTAL_2 - RIGHT_TOTAL_2",
   "color": "#EC864B",
   "data_source": "Calculated Amount",
   "display_name": "P&L Balance Check (should be zero)",
   "fieldtype": "",
   "hidden_calculation": 0,
   "hide_when_empty": 1,
   "include_in_charts": 0,
   "indentation_level": 0,
   "italic_text": 1,
   "reference_code": "PL_VALIDATION",
   "reverse_sign": 0
  },
  {
   "advanced_filtering": 0,
   "balance_type": "Period Movement (Debits - Credits)",
   "bold_text": 0,
   "calculation_formula": "[\"root_type\", \"=\", \"Income\"]",
   "data_source": "Account Data",
   "display_name": "Total Income",
   "fieldtype": "",
   "hidden_calculation": 1,
   "hide_when_empty": 0,
   "include_in_charts": 1,
   "indentation_level": 0,
   "italic_text": 0,
   "reference_code": "ACT_TOTAL_INCOME",
   "reverse_sign": 1
  },
  {
   "advanced_filtering": 0,
   "balance_type": "Period Movement (Debits - Credits)",
   "bold_text": 0,
   "calculation_formula": "[\"root_type\", \"=\", \"Expense\"]",
   "data_source": "Account Data",
   "display_name": "Total Expenses",
   "fieldtype": "",
   "hidden_calculation": 1,
   "hide_when_empty": 0,
   "include_in_charts": 1,
   "indentation_level": 0,
   "italic_text": 0,
   "reference_code": "ACT_TOTAL_EXPENSES",
   "reverse_sign": 0
  },
  {
   "advanced_filtering": 0,
   "balance_type": "",
   "bold_text": 0,
   "calculation_formula": "ACT_TOTAL_INCOME - ACT_TOTAL_EXPENSES",
   "data_source": "Calculated Amount",
   "display_name": "Net Profit",
   "fieldtype": "",
   "hidden_calculation": 1,
   "hide_when_empty": 0,
   "include_in_charts": 1,
   "indentation_level": 0,
   "italic_text": 0,
   "reference_code": "ACT_NET_PROFIT",
   "reverse_sign": 0
  },
  {
   "advanced_filtering": 0,
   "balance_type": "",
   "bold_text": 0,
   "calculation_formula": "NET_PROFIT_LEFT - NET_LOSS_RIGHT",
   "data_source": "Calculated Amount",
   "display_name": "Calculated Net Profit",
   "fieldtype": "",
   "hidden_calculation": 1,
   "hide_when_empty": 0,
   "include_in_charts": 0,
   "indentation_level": 0,
   "italic_text": 0,
   "reference_code": "CALC_NET_PROFIT",
   "reverse_sign": 0
  },
  {
   "advanced_filtering": 0,
   "balance_type": "",
   "bold_text": 1,
   "calculation_formula": "CALC_NET_PROFIT - ACT_NET_PROFIT",
   "color": "#CB2929",
   "data_source": "Calculated Amount",
   "display_name": "VARIANCE (Calculated vs Actual - should be zero)",
   "fieldtype": "",
   "hidden_calculation": 0,
   "hide_when_empty": 1,
   "include_in_charts": 0,
   "indentation_level": 0,
   "italic_text": 0,
   "reference_code": "VARIANCE",
   "reverse_sign": 0
  },
  {
   "advanced_filtering": 0,
   "balance_type": "",
   "bold_text": 0,
   "data_source": "Blank Line",
   "fieldtype": "",
   "hidden_calculation": 0,
   "hide_when_empty": 0,
   "include_in_charts": 0,
   "indentation_level": 0,
   "italic_text": 0,
   "reverse_sign": 0
  },
  {
   "advanced_filtering": 0,
   "balance_type": "",
   "bold_text": 1,
   "data_source": "Blank Line",
   "display_name": "KEY PERFORMANCE METRICS",
   "fieldtype": "",
   "hidden_calculation": 0,
   "hide_when_empty": 0,
   "include_in_charts": 0,
   "indentation_level": 0,
   "italic_text": 0,
   "reference_code": "METRICS_HEADER",
   "reverse_sign": 0
  },
  {
   "advanced_filtering": 0,
   "balance_type": "",
   "bold_text": 0,
   "calculation_formula": "((GP_CD_LEFT - GL_CD_RIGHT) / INC_SALES * 100) if INC_SALES != 0 else 0",
   "data_source": "Calculated Amount",
   "display_name": "Gross Profit %",
   "fieldtype": "Percent",
   "hidden_calculation": 0,
   "hide_when_empty": 0,
   "include_in_charts": 0,
   "indentation_level": 1,
   "italic_text": 1,
   "reference_code": "GP_PERCENT",
   "reverse_sign": 0
  },
  {
   "advanced_filtering": 0,
   "balance_type": "",
   "bold_text": 0,
   "calculation_formula": "(CALC_NET_PROFIT / INC_SALES * 100) if INC_SALES != 0 else 0",
   "data_source": "Calculated Amount",
   "display_name": "Net Profit %",
   "fieldtype": "Percent",
   "hidden_calculation": 0,
   "hide_when_empty": 0,
   "include_in_charts": 0,
   "indentation_level": 1,
   "italic_text": 1,
   "reference_code": "NP_PERCENT",
   "reverse_sign": 0
  },
  {
   "advanced_filtering": 0,
   "balance_type": "",
   "bold_text": 0,
   "calculation_formula": "((EXP_ADMIN + EXP_SELLING + EXP_OTHER) / INC_SALES * 100) if INC_SALES != 0 else 0",
   "data_source": "Calculated Amount",
   "display_name": "Operating Expense Ratio %",
   "fieldtype": "Percent",
   "hidden_calculation": 0,
   "hide_when_empty": 0,
   "include_in_charts": 0,
   "indentation_level": 1,
   "italic_text": 1,
   "reference_code": "EXPENSE_RATIO",
   "reverse_sign": 0
  }
 ],
 "template_name": "Horizontal Profit and Loss (Columnar)"
}
